[
  {
    "Default": {
      "$type": "ConfigAbility",
      "abilityName": "ActivityAbility_FreminetLoseHpWQ",
      "abilitySpecials": {
        "LoseHPInterval": 1,
        "SafeHPRatio": 0.1,
        "LoseHPRatio_Default": 0.02,
        "LoseHPRatio_1": 0.025,
        "LoseHPRatio_2": 0.03,
        "LoseHPRatio_3": 0.035,
        "LoseHPRatio_4": 0.04,
        "LoseHPRatio_5": 0.045,
        "LoseHPRatio_Max": 0.05
      },
      "modifiers": {
        "UNIQUE_FreminetLoseHpWQ_Handler": {
          "modifierName": "",
          "isUnique": true,
          "bonusCriticalHurt": 100,
          "thinkInterval": "LoseHPInterval",
          "onAdded": [
            {
              "$type": "AttachEffect",
              "HMGKAKGAJLE": "Eff_FreminetLoseHp_Loop"
            }
          ],
          "onThinkInterval": [
            {
              "$type": "ApplyModifier",
              "modifierName": "FreminetLoseHpWQ_Effect_Handler"
            },
            {
              "$type": "AddGlobalValue",
              "value": 0.5,
              "key": "_ABILITY_FreminetLoseHpWQ_LowHPTriggerLoseHP_Layer",
              "useLimitRange": true,
              "maxValue": 6,
              "minValue": 0
            }
          ]
        },
        "FreminetLoseHpWQ_Effect_Handler": {
          "modifierName": "",
          "duration": 0.1,
          "bonusCriticalHurt": 100,
          "onAdded": [
            {
              "$type": "Predicated",
              "targetPredicates": [
                {
                  "$type": "GNCFFIEOGKB",
                  "key": "_ABILITY_FreminetLoseHpWQ_LowHPTriggerLoseHP_Layer",
                  "value": 0
                }
              ],
              "successActions": [
                {
                  "$type": "LoseHP",
                  "MFEAHHOOPDM": "LoseHPRatio_Default",
                  "lethal": false,
                  "cdRatio": ""
                },
                {
                  "$type": "Predicated",
                  "targetPredicates": [
                    {
                      "$type": "FKLNCLMEDJL",
                      "logic": "LesserOrEqual",
                      "MKPGBIBHECC": "SafeHPRatio"
                    }
                  ],
                  "successActions": [
                    {
                      "$type": "CallLuaTask",
                      "targetAlias": "4008",
                      "valueString": "FreminetLoseHpWQ"
                    }
                  ]
                }
              ]
            },
            {
              "$type": "Predicated",
              "targetPredicates": [
                {
                  "$type": "GNCFFIEOGKB",
                  "key": "_ABILITY_FreminetLoseHpWQ_LowHPTriggerLoseHP_Layer",
                  "value": 0.5
                }
              ],
              "successActions": [
                {
                  "$type": "LoseHP",
                  "MFEAHHOOPDM": "LoseHPRatio_Default",
                  "lethal": false,
                  "cdRatio": ""
                },
                {
                  "$type": "Predicated",
                  "targetPredicates": [
                    {
                      "$type": "FKLNCLMEDJL",
                      "logic": "LesserOrEqual",
                      "MKPGBIBHECC": "SafeHPRatio"
                    }
                  ],
                  "successActions": [
                    {
                      "$type": "CallLuaTask",
                      "targetAlias": "4008",
                      "valueString": "FreminetLoseHpWQ"
                    }
                  ]
                }
              ]
            },
            {
              "$type": "Predicated",
              "targetPredicates": [
                {
                  "$type": "GNCFFIEOGKB",
                  "key": "_ABILITY_FreminetLoseHpWQ_LowHPTriggerLoseHP_Layer",
                  "value": 1
                }
              ],
              "successActions": [
                {
                  "$type": "LoseHP",
                  "MFEAHHOOPDM": "LoseHPRatio_1",
                  "lethal": false,
                  "cdRatio": ""
                },
                {
                  "$type": "Predicated",
                  "targetPredicates": [
                    {
                      "$type": "FKLNCLMEDJL",
                      "logic": "LesserOrEqual",
                      "MKPGBIBHECC": "SafeHPRatio"
                    }
                  ],
                  "successActions": [
                    {
                      "$type": "CallLuaTask",
                      "targetAlias": "4008",
                      "valueString": "FreminetLoseHpWQ"
                    }
                  ]
                }
              ]
            },
            {
              "$type": "Predicated",
              "targetPredicates": [
                {
                  "$type": "GNCFFIEOGKB",
                  "key": "_ABILITY_FreminetLoseHpWQ_LowHPTriggerLoseHP_Layer",
                  "value": 1.5
                }
              ],
              "successActions": [
                {
                  "$type": "LoseHP",
                  "MFEAHHOOPDM": "LoseHPRatio_1",
                  "lethal": false,
                  "cdRatio": ""
                },
                {
                  "$type": "Predicated",
                  "targetPredicates": [
                    {
                      "$type": "FKLNCLMEDJL",
                      "logic": "LesserOrEqual",
                      "MKPGBIBHECC": "SafeHPRatio"
                    }
                  ],
                  "successActions": [
                    {
                      "$type": "CallLuaTask",
                      "targetAlias": "4008",
                      "valueString": "FreminetLoseHpWQ"
                    }
                  ]
                }
              ]
            },
            {
              "$type": "Predicated",
              "targetPredicates": [
                {
                  "$type": "GNCFFIEOGKB",
                  "key": "_ABILITY_FreminetLoseHpWQ_LowHPTriggerLoseHP_Layer",
                  "value": 2
                }
              ],
              "successActions": [
                {
                  "$type": "LoseHP",
                  "MFEAHHOOPDM": "LoseHPRatio_2",
                  "lethal": false,
                  "cdRatio": ""
                },
                {
                  "$type": "Predicated",
                  "targetPredicates": [
                    {
                      "$type": "FKLNCLMEDJL",
                      "logic": "LesserOrEqual",
                      "MKPGBIBHECC": "SafeHPRatio"
                    }
                  ],
                  "successActions": [
                    {
                      "$type": "CallLuaTask",
                      "targetAlias": "4008",
                      "valueString": "FreminetLoseHpWQ"
                    }
                  ]
                }
              ]
            },
            {
              "$type": "Predicated",
              "targetPredicates": [
                {
                  "$type": "GNCFFIEOGKB",
                  "key": "_ABILITY_FreminetLoseHpWQ_LowHPTriggerLoseHP_Layer",
                  "value": 2.5
                }
              ],
              "successActions": [
                {
                  "$type": "LoseHP",
                  "MFEAHHOOPDM": "LoseHPRatio_2",
                  "lethal": false,
                  "cdRatio": ""
                },
                {
                  "$type": "Predicated",
                  "targetPredicates": [
                    {
                      "$type": "FKLNCLMEDJL",
                      "logic": "LesserOrEqual",
                      "MKPGBIBHECC": "SafeHPRatio"
                    }
                  ],
                  "successActions": [
                    {
                      "$type": "CallLuaTask",
                      "targetAlias": "4008",
                      "valueString": "FreminetLoseHpWQ"
                    }
                  ]
                }
              ]
            },
            {
              "$type": "Predicated",
              "targetPredicates": [
                {
                  "$type": "GNCFFIEOGKB",
                  "key": "_ABILITY_FreminetLoseHpWQ_LowHPTriggerLoseHP_Layer",
                  "value": 3
                }
              ],
              "successActions": [
                {
                  "$type": "LoseHP",
                  "MFEAHHOOPDM": "LoseHPRatio_3",
                  "lethal": false,
                  "cdRatio": ""
                },
                {
                  "$type": "Predicated",
                  "targetPredicates": [
                    {
                      "$type": "FKLNCLMEDJL",
                      "logic": "LesserOrEqual",
                      "MKPGBIBHECC": "SafeHPRatio"
                    }
                  ],
                  "successActions": [
                    {
                      "$type": "CallLuaTask",
                      "targetAlias": "4008",
                      "valueString": "FreminetLoseHpWQ"
                    }
                  ]
                }
              ]
            },
            {
              "$type": "Predicated",
              "targetPredicates": [
                {
                  "$type": "GNCFFIEOGKB",
                  "key": "_ABILITY_FreminetLoseHpWQ_LowHPTriggerLoseHP_Layer",
                  "value": 3.5
                }
              ],
              "successActions": [
                {
                  "$type": "LoseHP",
                  "MFEAHHOOPDM": "LoseHPRatio_3",
                  "lethal": false,
                  "cdRatio": ""
                },
                {
                  "$type": "Predicated",
                  "targetPredicates": [
                    {
                      "$type": "FKLNCLMEDJL",
                      "logic": "LesserOrEqual",
                      "MKPGBIBHECC": "SafeHPRatio"
                    }
                  ],
                  "successActions": [
                    {
                      "$type": "CallLuaTask",
                      "targetAlias": "4008",
                      "valueString": "FreminetLoseHpWQ"
                    }
                  ]
                }
              ]
            },
            {
              "$type": "Predicated",
              "targetPredicates": [
                {
                  "$type": "GNCFFIEOGKB",
                  "key": "_ABILITY_FreminetLoseHpWQ_LowHPTriggerLoseHP_Layer",
                  "value": 4
                }
              ],
              "successActions": [
                {
                  "$type": "LoseHP",
                  "MFEAHHOOPDM": "LoseHPRatio_4",
                  "lethal": false,
                  "cdRatio": ""
                },
                {
                  "$type": "Predicated",
                  "targetPredicates": [
                    {
                      "$type": "FKLNCLMEDJL",
                      "logic": "LesserOrEqual",
                      "MKPGBIBHECC": "SafeHPRatio"
                    }
                  ],
                  "successActions": [
                    {
                      "$type": "CallLuaTask",
                      "targetAlias": "4008",
                      "valueString": "FreminetLoseHpWQ"
                    }
                  ]
                }
              ]
            },
            {
              "$type": "Predicated",
              "targetPredicates": [
                {
                  "$type": "GNCFFIEOGKB",
                  "key": "_ABILITY_FreminetLoseHpWQ_LowHPTriggerLoseHP_Layer",
                  "value": 4.5
                }
              ],
              "successActions": [
                {
                  "$type": "LoseHP",
                  "MFEAHHOOPDM": "LoseHPRatio_4",
                  "lethal": false,
                  "cdRatio": ""
                },
                {
                  "$type": "Predicated",
                  "targetPredicates": [
                    {
                      "$type": "FKLNCLMEDJL",
                      "logic": "LesserOrEqual",
                      "MKPGBIBHECC": "SafeHPRatio"
                    }
                  ],
                  "successActions": [
                    {
                      "$type": "CallLuaTask",
                      "targetAlias": "4008",
                      "valueString": "FreminetLoseHpWQ"
                    }
                  ]
                }
              ]
            },
            {
              "$type": "Predicated",
              "targetPredicates": [
                {
                  "$type": "GNCFFIEOGKB",
                  "key": "_ABILITY_FreminetLoseHpWQ_LowHPTriggerLoseHP_Layer",
                  "value": 5
                }
              ],
              "successActions": [
                {
                  "$type": "LoseHP",
                  "MFEAHHOOPDM": "LoseHPRatio_5",
                  "lethal": false,
                  "cdRatio": ""
                },
                {
                  "$type": "Predicated",
                  "targetPredicates": [
                    {
                      "$type": "FKLNCLMEDJL",
                      "logic": "LesserOrEqual",
                      "MKPGBIBHECC": "SafeHPRatio"
                    }
                  ],
                  "successActions": [
                    {
                      "$type": "CallLuaTask",
                      "targetAlias": "4008",
                      "valueString": "FreminetLoseHpWQ"
                    }
                  ]
                }
              ]
            },
            {
              "$type": "Predicated",
              "targetPredicates": [
                {
                  "$type": "GNCFFIEOGKB",
                  "key": "_ABILITY_FreminetLoseHpWQ_LowHPTriggerLoseHP_Layer",
                  "value": 5.5
                }
              ],
              "successActions": [
                {
                  "$type": "LoseHP",
                  "MFEAHHOOPDM": "LoseHPRatio_5",
                  "lethal": false,
                  "cdRatio": ""
                },
                {
                  "$type": "Predicated",
                  "targetPredicates": [
                    {
                      "$type": "FKLNCLMEDJL",
                      "logic": "LesserOrEqual",
                      "MKPGBIBHECC": "SafeHPRatio"
                    }
                  ],
                  "successActions": [
                    {
                      "$type": "CallLuaTask",
                      "targetAlias": "4008",
                      "valueString": "FreminetLoseHpWQ"
                    }
                  ]
                }
              ]
            },
            {
              "$type": "Predicated",
              "targetPredicates": [
                {
                  "$type": "GNCFFIEOGKB",
                  "key": "_ABILITY_FreminetLoseHpWQ_LowHPTriggerLoseHP_Layer",
                  "value": 6
                }
              ],
              "successActions": [
                {
                  "$type": "LoseHP",
                  "MFEAHHOOPDM": "LoseHPRatio_Max",
                  "lethal": false,
                  "cdRatio": ""
                },
                {
                  "$type": "Predicated",
                  "targetPredicates": [
                    {
                      "$type": "FKLNCLMEDJL",
                      "logic": "LesserOrEqual",
                      "MKPGBIBHECC": "SafeHPRatio"
                    }
                  ],
                  "successActions": [
                    {
                      "$type": "CallLuaTask",
                      "targetAlias": "4008",
                      "valueString": "FreminetLoseHpWQ"
                    }
                  ]
                }
              ]
            }
          ]
        }
      },
      "onAdded": [
        {
          "$type": "SetGlobalValue",
          "target": "Team",
          "repeatTimes": true,
          "value": 0,
          "key": "_ABILITY_FreminetLoseHpWQ_LowHPTriggerLoseHP_Layer",
          "maxValue": 0,
          "minValue": 0
        },
        {
          "$type": "AttachModifier",
          "target": "CurTeamAvatars",
          "modifierName": "UNIQUE_FreminetLoseHpWQ_Handler"
        }
      ],
      "isDynamicAbility": true
    }
  }
]
