{
  "Escoffier_SkillUpgrade_1": [
    {
      "$type": "ModifyAbility",
      "paramDelta": "%1",
      "paramSpecial": "Escoffier_NormalAttack_01",
      "abilityName": "Avatar_Escoffier_NormalAttack_DamageHandler",
      "PAECKGNGCEE": true,
      "IANOLKDGDKE": "All"
    },
    {
      "$type": "ModifyAbility",
      "paramDelta": "%2",
      "paramSpecial": "Escoffier_NormalAttack_02",
      "abilityName": "Avatar_Escoffier_NormalAttack_DamageHandler",
      "PAECKGNGCEE": true,
      "IANOLKDGDKE": "All"
    },
    {
      "$type": "ModifyAbility",
      "paramDelta": "%3",
      "paramSpecial": "Escoffier_NormalAttack_03_01",
      "abilityName": "Avatar_Escoffier_NormalAttack_DamageHandler",
      "PAECKGNGCEE": true,
      "IANOLKDGDKE": "All"
    },
    {
      "$type": "ModifyAbility",
      "paramDelta": "%4",
      "paramSpecial": "Escoffier_NormalAttack_03_02",
      "abilityName": "Avatar_Escoffier_NormalAttack_DamageHandler",
      "PAECKGNGCEE": true,
      "IANOLKDGDKE": "All"
    },
    {
      "$type": "ModifyAbility",
      "paramDelta": "%5",
      "paramSpecial": "Escoffier_ExtraAttack",
      "abilityName": "Avatar_Escoffier_NormalAttack_DamageHandler",
      "PAECKGNGCEE": true,
      "IANOLKDGDKE": "All"
    },
    {
      "$type": "ModifyAbility",
      "paramDelta": "%6",
      "paramSpecial": "ExtraAttack_Pole_Stamina_Cost",
      "abilityName": "Avatar_Escoffier_ExtraAttack",
      "PAECKGNGCEE": true,
      "IANOLKDGDKE": "All"
    },
    {
      "$type": "ModifyAbility",
      "paramDelta": "%7",
      "paramSpecial": "FallingAnthem_Normal_Loop_Damage",
      "abilityName": "Avatar_Escoffier_FallingAnthem",
      "PAECKGNGCEE": true,
      "IANOLKDGDKE": "All"
    },
    {
      "$type": "ModifyAbility",
      "paramDelta": "%8",
      "paramSpecial": "FallingAnthem_Normal_Rank_1_Damage",
      "abilityName": "Avatar_Escoffier_FallingAnthem",
      "PAECKGNGCEE": true,
      "IANOLKDGDKE": "All"
    },
    {
      "$type": "ModifyAbility",
      "paramDelta": "%9",
      "paramSpecial": "FallingAnthem_Normal_Rank_2_Damage",
      "abilityName": "Avatar_Escoffier_FallingAnthem",
      "PAECKGNGCEE": true,
      "IANOLKDGDKE": "All"
    }
  ],
  "Escoffier_SkillUpgrade_2": [
    {
      "$type": "ModifyAbility",
      "paramDelta": "%1",
      "paramSpecial": "ElementalArt_Create_Damage",
      "abilityName": "Avatar_Escoffier_ElementalArt",
      "PAECKGNGCEE": true,
      "IANOLKDGDKE": "All"
    },
    {
      "$type": "ModifyAbility",
      "paramDelta": "%2",
      "paramSpecial": "ElementalArt_Bullet_Damage",
      "abilityName": "Bullet_Escoffier_ElementalArt_Attacker_01",
      "PAECKGNGCEE": true,
      "IANOLKDGDKE": "All"
    },
    {
      "$type": "ModifyAbility",
      "paramDelta": "%3",
      "paramSpecial": "Dur",
      "abilityName": "Avatar_Escoffier_ElementalArt",
      "PAECKGNGCEE": true,
      "IANOLKDGDKE": "All"
    },
    {
      "$type": "ModifyAbility",
      "paramDelta": "%4",
      "paramSpecial": "Arkhe_Damage",
      "abilityName": "SkillObj_Escoffier_Pneuma_Attack",
      "PAECKGNGCEE": true,
      "IANOLKDGDKE": "All"
    },
    {
      "$type": "ModifyAbility",
      "paramDelta": "%5",
      "paramSpecial": "ArkheGrade_CD",
      "abilityName": "Avatar_Escoffier_ElementalArt",
      "PAECKGNGCEE": true,
      "IANOLKDGDKE": "All"
    },
    {
      "$type": "ModifyAbility",
      "paramDelta": "%2",
      "paramSpecial": "ElementalArt_Bullet_Damage",
      "abilityName": "Bullet_Escoffier_Constellation_Split",
      "PAECKGNGCEE": true,
      "IANOLKDGDKE": "All"
    }
  ],
  "Escoffier_SkillUpgrade_3": [
    {
      "$type": "ModifyAbility",
      "paramDelta": "%1",
      "paramSpecial": "ElementalBurst_Damage",
      "abilityName": "Avatar_Escoffier_ElementalBurst",
      "PAECKGNGCEE": true,
      "IANOLKDGDKE": "All"
    },
    {
      "$type": "ModifyAbility",
      "paramDelta": "%2",
      "paramSpecial": "ElementalBurst_Heal_AttackRatio",
      "abilityName": "Avatar_Escoffier_ElementalBurst",
      "PAECKGNGCEE": true,
      "IANOLKDGDKE": "All"
    },
    {
      "$type": "ModifyAbility",
      "paramDelta": "%3",
      "paramSpecial": "ElementalBurst_Heal_Amount",
      "abilityName": "Avatar_Escoffier_ElementalBurst",
      "PAECKGNGCEE": true,
      "IANOLKDGDKE": "All"
    }
  ],
  "Escoffier_PermanentSkill_1": [
    {
      "$type": "ModifyAbility",
      "paramDelta": "%1",
      "paramSpecial": "Escoffier_HealHP_Hot_Ratio",
      "abilityName": "Avatar_Escoffier_ElementalBurst",
      "PAECKGNGCEE": true,
      "IANOLKDGDKE": "All"
    },
    {
      "$type": "ModifyAbility",
      "paramDelta": "%2",
      "paramSpecial": "Dur",
      "abilityName": "Avatar_Escoffier_ElementalBurst",
      "PAECKGNGCEE": true,
      "IANOLKDGDKE": "All"
    },
    {
      "$type": "UnlockTalentParam",
      "talentParam": "Escoffier_PermanentSkill_1",
      "abilityName": "Avatar_Escoffier_ElementalBurst",
      "PAECKGNGCEE": true,
      "IANOLKDGDKE": "All"
    }
  ],
  "Escoffier_PermanentSkill_2": [
    {
      "$type": "AddAbility",
      "abilityName": "Avatar_Escoffier_PermanentSkill_2_SubHurtDelta",
      "PAECKGNGCEE": true,
      "IANOLKDGDKE": "All"
    },
    {
      "$type": "ModifyAbility",
      "paramDelta": "%1",
      "paramSpecial": "AddHurtDelta_Level01",
      "abilityName": "Avatar_Escoffier_PermanentSkill_2_SubHurtDelta",
      "PAECKGNGCEE": true,
      "IANOLKDGDKE": "All"
    },
    {
      "$type": "ModifyAbility",
      "paramDelta": "%2",
      "paramSpecial": "AddHurtDelta_Level02",
      "abilityName": "Avatar_Escoffier_PermanentSkill_2_SubHurtDelta",
      "PAECKGNGCEE": true,
      "IANOLKDGDKE": "All"
    },
    {
      "$type": "ModifyAbility",
      "paramDelta": "%3",
      "paramSpecial": "AddHurtDelta_Level03",
      "abilityName": "Avatar_Escoffier_PermanentSkill_2_SubHurtDelta",
      "PAECKGNGCEE": true,
      "IANOLKDGDKE": "All"
    },
    {
      "$type": "ModifyAbility",
      "paramDelta": "%4",
      "paramSpecial": "AddHurtDelta_Level04",
      "abilityName": "Avatar_Escoffier_PermanentSkill_2_SubHurtDelta",
      "PAECKGNGCEE": true,
      "IANOLKDGDKE": "All"
    },
    {
      "$type": "ModifyAbility",
      "paramDelta": "%5",
      "paramSpecial": "Dura",
      "abilityName": "Avatar_Escoffier_PermanentSkill_2_SubHurtDelta",
      "PAECKGNGCEE": true,
      "IANOLKDGDKE": "All"
    },
    {
      "$type": "UnlockTalentParam",
      "talentParam": "Escoffier_PermanentSkill_2",
      "abilityName": "Avatar_Escoffier_Constellation_1",
      "PAECKGNGCEE": true,
      "IANOLKDGDKE": "All"
    }
  ],
  "Escoffier_Constellation_1": [
    {
      "$type": "AddAbility",
      "abilityName": "Avatar_Escoffier_Constellation_1",
      "PAECKGNGCEE": true,
      "IANOLKDGDKE": "All"
    },
    {
      "$type": "ModifyAbility",
      "paramDelta": "%1",
      "paramSpecial": "CriticalHurtDelta",
      "abilityName": "Avatar_Escoffier_Constellation_1",
      "PAECKGNGCEE": true,
      "IANOLKDGDKE": "All"
    },
    {
      "$type": "ModifyAbility",
      "paramDelta": "%2",
      "paramSpecial": "Dura",
      "abilityName": "Avatar_Escoffier_Constellation_1",
      "PAECKGNGCEE": true,
      "IANOLKDGDKE": "All"
    }
  ],
  "Escoffier_Constellation_2": [
    {
      "$type": "AddAbility",
      "abilityName": "Avatar_Escoffier_Constellation_2",
      "PAECKGNGCEE": true,
      "IANOLKDGDKE": "All"
    },
    {
      "$type": "ModifyAbility",
      "paramDelta": "%1",
      "paramSpecial": "EDamageExtra_Buff_Time",
      "abilityName": "Avatar_Escoffier_Constellation_2",
      "PAECKGNGCEE": true,
      "IANOLKDGDKE": "All"
    },
    {
      "$type": "ModifyAbility",
      "paramDelta": "%2",
      "paramSpecial": "AttackExtraRatio",
      "abilityName": "Avatar_Escoffier_Constellation_2",
      "PAECKGNGCEE": true,
      "IANOLKDGDKE": "All"
    },
    {
      "$type": "ModifyAbility",
      "paramDelta": "%3",
      "paramSpecial": "Escoffier_Constellation_MaxCount",
      "abilityName": "Avatar_Escoffier_Constellation_2",
      "PAECKGNGCEE": true,
      "IANOLKDGDKE": "All"
    }
  ],
  "Escoffier_Constellation_3": [
    {
      "$type": "AddTalentExtraLevel",
      "talentType": "AvatarSkill",
      "talentIndex": 2,
      "extraLevel": 3,
      "PAECKGNGCEE": true,
      "IANOLKDGDKE": "All"
    }
  ],
  "Escoffier_Constellation_4": [
    {
      "$type": "UnlockTalentParam",
      "talentParam": "Escoffier_Constellation_4",
      "abilityName": "Avatar_Escoffier_ElementalBurst",
      "PAECKGNGCEE": true,
      "IANOLKDGDKE": "All"
    }
  ],
  "Escoffier_Constellation_5": [
    {
      "$type": "AddTalentExtraLevel",
      "talentType": "AvatarSkill",
      "talentIndex": 9,
      "extraLevel": 3,
      "PAECKGNGCEE": true,
      "IANOLKDGDKE": "All"
    }
  ],
  "Escoffier_Constellation_6": [
    {
      "$type": "UnlockTalentParam",
      "talentParam": "Escoffier_Constellation_6",
      "abilityName": "Avatar_Escoffier_ElementalArt",
      "PAECKGNGCEE": true,
      "IANOLKDGDKE": "All"
    },
    {
      "$type": "ModifyAbility",
      "paramDelta": "%1",
      "paramSpecial": "ElementalArt_BigBullet_Damage",
      "abilityName": "Bullet_Escoffier_ElementalArt_Attacker_02",
      "PAECKGNGCEE": true,
      "IANOLKDGDKE": "All"
    }
  ]
}
